coscmos/__init__.py
coscmos/_version.py
coscmos/core.py
coscmos/_tests/__init__.py
coscmos/_tests/conftest.py
coscmos/_tests/test_core.py
coscmos-0.0.1.dist-info/LICENSE
coscmos-0.0.1.dist-info/METADATA
coscmos-0.0.1.dist-info/WHEEL
coscmos-0.0.1.dist-info/top_level.txt
coscmos-0.0.1.dist-info/RECORD
