Metadata-Version: 2.1
Name: coscmos
Version: 0.0.1
Summary: cosCMOS ( "correct sCMOS", pronounced as cosmos ) is a Python package designed to cancel the fixed-pattern noise of sCMOS cameras.
Home-page: https://github.com/LemonJust/coscmos
Author: Anna Nadtochiy
Author-email: lemonjustgithub@gmail.com
License: BSD-3-Clause
Project-URL: Bug Tracker, https://github.com/LemonJust/coscmos/issues
Project-URL: Documentation, https://github.com/LemonJust/coscmos#README.md
Project-URL: Source Code, https://github.com/LemonJust/coscmos
Project-URL: User Support, https://github.com/LemonJust/coscmos/issues
Classifier: Development Status :: 2 - Pre-Alpha
Classifier: Intended Audience :: Developers
Classifier: License :: OSI Approved :: BSD License
Classifier: Operating System :: OS Independent
Classifier: Programming Language :: Python
Classifier: Programming Language :: Python :: 3
Classifier: Programming Language :: Python :: 3 :: Only
Classifier: Programming Language :: Python :: 3.8
Classifier: Programming Language :: Python :: 3.9
Classifier: Programming Language :: Python :: 3.10
Classifier: Topic :: Scientific/Engineering :: Image Processing
Requires-Python: >=3.8
License-File: LICENSE
Requires-Dist: vodex (==1.0.11)
Provides-Extra: testing
Requires-Dist: tox ; extra == 'testing'
Requires-Dist: pytest ; extra == 'testing'
Requires-Dist: pytest-cov ; extra == 'testing'
